CHANGES.rst
LICENSE
README.rst
aiocurrencylayer/__init__.py
aiocurrencylayer/exceptions.py
aiocurrencylayer-1.0.6.dist-info/LICENSE
aiocurrencylayer-1.0.6.dist-info/METADATA
aiocurrencylayer-1.0.6.dist-info/WHEEL
aiocurrencylayer-1.0.6.dist-info/RECORD
