Metadata-Version: 2.1
Name: aiocurrencylayer
Version: 1.0.6
Summary: Python client for interacting with the CurrencyLayer API
Home-page: https://github.com/home-assistant-ecosystem/aiocurrencylayer
License: MIT
Author: Fabian Affolter
Author-email: fabian@affolter-engineering.ch
Requires-Python: >=3.10,<4.0
Classifier: License :: OSI Approved :: MIT License
Classifier: Programming Language :: Python :: 3
Classifier: Programming Language :: Python :: 3.10
Classifier: Programming Language :: Python :: 3.11
Classifier: Programming Language :: Python :: 3.12
Requires-Dist: httpx (>=0.26,<1)
